pyabi_chaiscript/__init__.py
PyABI_CHAISCRIPT-0.0.42.dist-info/LICENSE.md
PyABI_CHAISCRIPT-0.0.42.dist-info/METADATA
PyABI_CHAISCRIPT-0.0.42.dist-info/WHEEL
PyABI_CHAISCRIPT-0.0.42.dist-info/top_level.txt
PyABI_CHAISCRIPT-0.0.42.dist-info/RECORD
