Metadata-Version: 2.1
Name: PyABI-CHAISCRIPT
Version: 0.0.42
Summary: PyABI_CHIASCRIPT Implements the ChiaScript C++ Engine
Home-page: https://github.com/PyABI/PyABI_CHAISCRIPT
Author: Scott McCallum (https github.com scott91e1)
Author-email: Scott.McCallum@intermine.com
License: UNKNOWN
Platform: UNKNOWN
Classifier: Programming Language :: Python :: 3
Classifier: License :: OSI Approved :: MIT License
Classifier: Operating System :: OS Independent
Requires-Python: >=3.6
